dashborg/__init__.py
dashborg/db3.py
dashborg/dbcrypto.py
dashborg/dbu.py
dashborg/dborgproto/__init__.py
dashborg/dborgproto/dborgproto_pb2.py
dashborg/dborgproto/dborgproto_pb2_grpc.py
dashborg_python_sdk-0.4.0.dev5.dist-info/LICENSE
dashborg_python_sdk-0.4.0.dev5.dist-info/METADATA
dashborg_python_sdk-0.4.0.dev5.dist-info/WHEEL
dashborg_python_sdk-0.4.0.dev5.dist-info/top_level.txt
dashborg_python_sdk-0.4.0.dev5.dist-info/RECORD
