Metadata-Version: 2.1
Name: dashborg-python-sdk
Version: 0.4.0.dev5
Summary: Dashborg Python SDK
Home-page: https://github.com/sawka/dashborg-python-sdk
Author: Michael Sawka
Author-email: mike@dashborg.net
License: UNKNOWN
Platform: UNKNOWN
Classifier: Programming Language :: Python :: 3
Classifier: License :: OSI Approved :: MIT License
Classifier: Operating System :: OS Independent
Requires-Python: >=3.6
Requires-Dist: aiofiles
Requires-Dist: cffi
Requires-Dist: cryptography
Requires-Dist: ecdsa
Requires-Dist: grpcio
Requires-Dist: grpcio-tools
Requires-Dist: protobuf
Requires-Dist: pycparser
Requires-Dist: six
Requires-Dist: pyjwt
Requires-Dist: watchdog
Requires-Dist: aiohttp
